LICENSE
MANIFEST.in
README.rst
setup.cfg
setup.py
codemirror2/__init__.py
codemirror2/widgets.py
codemirror2/static/codemirror2/.git
codemirror2/static/codemirror2/.gitattributes
codemirror2/static/codemirror2/.gitignore
codemirror2/static/codemirror2/.travis.yml
codemirror2/static/codemirror2/AUTHORS
codemirror2/static/codemirror2/CONTRIBUTING.md
codemirror2/static/codemirror2/LICENSE
codemirror2/static/codemirror2/README.md
codemirror2/static/codemirror2/bower.json
codemirror2/static/codemirror2/index.html
codemirror2/static/codemirror2/package.json
codemirror2/static/codemirror2/addon/comment/comment.js
codemirror2/static/codemirror2/addon/comment/continuecomment.js
codemirror2/static/codemirror2/addon/dialog/dialog.css
codemirror2/static/codemirror2/addon/dialog/dialog.js
codemirror2/static/codemirror2/addon/display/fullscreen.css
codemirror2/static/codemirror2/addon/display/fullscreen.js
codemirror2/static/codemirror2/addon/display/placeholder.js
codemirror2/static/codemirror2/addon/display/rulers.js
codemirror2/static/codemirror2/addon/edit/closebrackets.js
codemirror2/static/codemirror2/addon/edit/closetag.js
codemirror2/static/codemirror2/addon/edit/continuelist.js
codemirror2/static/codemirror2/addon/edit/matchbrackets.js
codemirror2/static/codemirror2/addon/edit/matchtags.js
codemirror2/static/codemirror2/addon/edit/trailingspace.js
codemirror2/static/codemirror2/addon/fold/brace-fold.js
codemirror2/static/codemirror2/addon/fold/comment-fold.js
codemirror2/static/codemirror2/addon/fold/foldcode.js
codemirror2/static/codemirror2/addon/fold/foldgutter.css
codemirror2/static/codemirror2/addon/fold/foldgutter.js
codemirror2/static/codemirror2/addon/fold/indent-fold.js
codemirror2/static/codemirror2/addon/fold/markdown-fold.js
codemirror2/static/codemirror2/addon/fold/xml-fold.js
codemirror2/static/codemirror2/addon/hint/anyword-hint.js
codemirror2/static/codemirror2/addon/hint/css-hint.js
codemirror2/static/codemirror2/addon/hint/html-hint.js
django_codemirror2.egg-info/PKG-INFO
django_codemirror2.egg-info/SOURCES.txt
django_codemirror2.egg-info/dependency_links.txt
django_codemirror2.egg-info/top_level.txt
