Metadata-Version: 1.1
Name: django-codemirror2
Version: 0.1.3
Summary: Django widgets for replacing textareas with CodeMirror2, an in-browser code editor
Home-page: https://github.com/sk1p/django-codemirror2
Author: Alexander Clausen
Author-email: alex@gc-web.de
License: UNKNOWN
Platform: UNKNOWN
Classifier: Development Status :: 4 - Beta
Classifier: Environment :: Web Environment
Classifier: Framework :: Django
Classifier: Intended Audience :: Developers
Classifier: License :: OSI Approved :: MIT License
Classifier: Programming Language :: Python
Classifier: Programming Language :: JavaScript
Classifier: Topic :: Text Editors
